owly/__init__.py
owly/endpoint.py
owly-0.0.3.dist-info/LICENSE
owly-0.0.3.dist-info/WHEEL
owly-0.0.3.dist-info/METADATA
owly-0.0.3.dist-info/RECORD
